ap_mail/__init__.py
ap_mail/__version__.py
ap_mail/app.py
ap_mail/mail.py
ap_mail/mailrcv.py
ap_mail/mailsnd.py
ap_mail/parms.py
ap_mail/py.typed
ap_mail/task.py
ap_mail/ioc/jinja2_.py
ap_mail/ioc/yaml_.py
ap_mail-2.0.0.20251021.dist-info/licenses/LICENSE.txt
ap_mail-2.0.0.20251021.dist-info/METADATA
ap_mail-2.0.0.20251021.dist-info/WHEEL
ap_mail-2.0.0.20251021.dist-info/entry_points.txt
ap_mail-2.0.0.20251021.dist-info/top_level.txt
ap_mail-2.0.0.20251021.dist-info/RECORD
