Metadata-Version: 2.4
Name: ap_mail
Version: 2.0.0.20251021
Summary: Application for Mailing
Author: Bernd Stroehle
Author-email: bernd.stroehle@gmail.com
Maintainer: Bernd Stroehle
Maintainer-email: bernd.stroehle@gmail.com
License-Expression: GPL-3.0-only WITH Classpath-exception-2.0 OR BSD-3-Clause
Project-URL: Source Code, https://github.com/bs2910/ap_mail/tree/master
Project-URL: Homepage, https://kosakya.de/
Project-URL: Documentation, https://ka-com.readthedocs.io/en/latest
Project-URL: Apache-2.0 License, https://apache.org/licenses/LICENSE-2.0
Project-URL: GPLv3 License, https://www.gnu.org/licenses/gpl-3.0.en.html
Classifier: Development Status :: 5 - Production/Stable
Classifier: Intended Audience :: Developers
Classifier: Operating System :: OS Independent
Classifier: Programming Language :: Python :: 3.11
Classifier: Natural Language :: English
Classifier: Topic :: Software Development :: Libraries :: Python Modules
Requires-Python: >=3.10
License-File: LICENSE.txt
Requires-Dist: Jinja2>=3.1.6
Requires-Dist: msal>=1.32.3
Requires-Dist: PyYAML>=6.0.3
Requires-Dist: ut_cli>=1.0.9.20251005
Requires-Dist: ut_com>=1.2.8.20251005
Requires-Dist: ut_dic>=1.4.9.20251005
Requires-Dist: ut_ioc>=1.1.5.20251006
Requires-Dist: ut_log>=1.3.1.20251001
Requires-Dist: ut_path>=1.3.5.20251005
Dynamic: license-file
